{
    "key": "group_6552275d5486d",
    "title": "Events Options",
    "fields": [
        {
            "key": "field_6552275d274e8",
            "label": "Pretix API Token",
            "name": "pretix_api_token",
            "aria-label": "",
            "type": "password",
            "instructions": "",
            "required": 0,
            "conditional_logic": 0,
            "wrapper": {
                "width": "",
                "class": "",
                "id": ""
            },
            "placeholder": "",
            "prepend": "",
            "append": ""
        },
        {
            "key": "field_655255d76ea4a",
            "label": "Cache Expiry (seconds)",
            "name": "cache_time",
            "aria-label": "",
            "type": "number",
            "instructions": "",
            "required": 1,
            "conditional_logic": 0,
            "wrapper": {
                "width": "",
                "class": "",
                "id": ""
            },
            "default_value": 3600,
            "min": "",
            "max": "",
            "placeholder": "",
            "step": -2,
            "prepend": "",
            "append": ""
        }
    ],
    "location": [
        [
            {
                "param": "options_page",
                "operator": "==",
                "value": "acf-options-events-options"
            }
        ]
    ],
    "menu_order": 0,
    "position": "normal",
    "style": "default",
    "label_placement": "top",
    "instruction_placement": "label",
    "hide_on_screen": "",
    "active": true,
    "description": "",
    "show_in_rest": 0,
    "display_title": ""
}